ai_code_forge_cli/__init__.py
ai_code_forge_cli/cli.py
ai_code_forge_cli/commands/__init__.py
ai_code_forge_cli/commands/init.py
ai_code_forge_cli/commands/status.py
ai_code_forge_cli/commands/update.py
ai_code_forge_cli/core/__init__.py
ai_code_forge_cli/core/deployer.py
ai_code_forge_cli/core/detector.py
ai_code_forge_cli/core/git.py
ai_code_forge_cli/core/git_wrapper.py
ai_code_forge_cli/core/state.py
ai_code_forge_cli/core/static.py
ai_code_forge_cli/core/templates.py
ai_code_forge_cli/templates/CLAUDE.md
ai_code_forge_cli/templates/CLAUDE.md.template
ai_code_forge_cli/templates/_claude/settings.json
ai_code_forge_cli/templates/_claude/agents/foundation/conflicts.md
ai_code_forge_cli/templates/_claude/agents/foundation/context.md
ai_code_forge_cli/templates/_claude/agents/foundation/critic.md
ai_code_forge_cli/templates/_claude/agents/foundation/patterns.md
ai_code_forge_cli/templates/_claude/agents/foundation/principles.md
ai_code_forge_cli/templates/_claude/agents/foundation/researcher.md
ai_code_forge_cli/templates/_claude/agents/specialists/code-cleaner.md
ai_code_forge_cli/templates/_claude/agents/specialists/constraint-solver.md
ai_code_forge_cli/templates/_claude/agents/specialists/git-workflow.md
ai_code_forge_cli/templates/_claude/agents/specialists/github-issues-workflow.md
ai_code_forge_cli/templates/_claude/agents/specialists/github-pr-workflow.md
ai_code_forge_cli/templates/_claude/agents/specialists/meta-programmer.md
ai_code_forge_cli/templates/_claude/agents/specialists/options-analyzer.md
ai_code_forge_cli/templates/_claude/agents/specialists/performance-optimizer.md
ai_code_forge_cli/templates/_claude/agents/specialists/prompt-engineer.md
ai_code_forge_cli/templates/_claude/agents/specialists/stack-advisor.md
ai_code_forge_cli/templates/_claude/agents/specialists/test-strategist.md
ai_code_forge_cli/templates/_claude/commands/deploy.md
ai_code_forge_cli/templates/_claude/commands/discuss.md
acforge-3.1.1.dist-info/METADATA
acforge-3.1.1.dist-info/WHEEL
acforge-3.1.1.dist-info/entry_points.txt
acforge-3.1.1.dist-info/RECORD
