Metadata-Version: 2.4
Name: acforge
Version: 3.1.1
Summary: acforge cli for AI Code Forge configuration management
Project-URL: Homepage, https://github.com/ondrasek/ai-code-forge
Project-URL: Repository, https://github.com/ondrasek/ai-code-forge
Project-URL: Issues, https://github.com/ondrasek/ai-code-forge/issues
Author-email: "Ondrej (Ondra) Krajicek" <me@ondrejkrajicek.com>
License: MIT
Keywords: ai,claude,cli,configuration,development,templates
Classifier: Development Status :: 3 - Alpha
Classifier: Intended Audience :: Developers
Classifier: License :: OSI Approved :: MIT License
Classifier: Programming Language :: Python :: 3
Classifier: Programming Language :: Python :: 3.9
Classifier: Programming Language :: Python :: 3.10
Classifier: Programming Language :: Python :: 3.11
Classifier: Programming Language :: Python :: 3.12
Classifier: Programming Language :: Python :: 3.13
Classifier: Topic :: Software Development
Classifier: Topic :: Software Development :: Code Generators
Classifier: Topic :: System :: Installation/Setup
Requires-Python: >=3.9
Requires-Dist: click>=8.0.0
Requires-Dist: jinja2>=3.1.0
Requires-Dist: pydantic>=2.0.0
